hssp/__init__.py
hssp/exception/__init__.py
hssp/exception/exception.py
hssp/logger/__init__.py
hssp/logger/handler.py
hssp/logger/log.py
hssp/models/__init__.py
hssp/models/config.py
hssp/models/net.py
hssp/network/__init__.py
hssp/network/net.py
hssp/network/downloader/__init__.py
hssp/network/downloader/aiohttp.py
hssp/network/downloader/base.py
hssp/network/downloader/curl_cffi.py
hssp/network/downloader/httpx.py
hssp/network/downloader/requests.py
hssp/network/downloader/requests_go.py
hssp/network/response/__init__.py
hssp/network/response/response.py
hssp/network/response/selector.py
hssp/settings/__init__.py
hssp/settings/setting_base.py
hssp/settings/settings.py
hssp/utils/__init__.py
hssp/utils/classes.py
hssp/utils/crypto.py
hssp/utils/rand.py
hssp/utils/time.py
hssp-0.4.18.dist-info/METADATA
hssp-0.4.18.dist-info/WHEEL
hssp-0.4.18.dist-info/licenses/LICENSE
hssp-0.4.18.dist-info/RECORD
