Metadata-Version: 2.4
Name: hssp
Version: 0.4.18
Summary: 一个简单快速的异步爬虫框架
Project-URL: homepage, https://github.com/x-haose/hssp
Project-URL: repository, https://github.com/x-haose/hssp
Project-URL: documentation, https://github.com/x-haose/hssp
Author-email: 昊色居士 <xhrtxh@gmail.com>
License-Expression: MIT
License-File: LICENSE
Keywords: 异步,爬虫,爬虫框架
Classifier: Development Status :: 4 - Beta
Classifier: Intended Audience :: Developers
Classifier: License :: OSI Approved :: MIT License
Classifier: Operating System :: MacOS :: MacOS X
Classifier: Operating System :: Microsoft :: Windows
Classifier: Operating System :: POSIX :: BSD
Classifier: Operating System :: POSIX :: Linux
Classifier: Programming Language :: Python :: 3.10
Classifier: Programming Language :: Python :: 3.11
Classifier: Programming Language :: Python :: 3.12
Classifier: Topic :: Internet :: WWW/HTTP
Classifier: Topic :: Software Development :: Libraries :: Application Frameworks
Classifier: Topic :: Software Development :: Libraries :: Python Modules
Requires-Python: >=3.10
Requires-Dist: aiohttp>=3.9.5
Requires-Dist: apscheduler>=3.10.4
Requires-Dist: blinker>=1.8.2
Requires-Dist: curl-cffi>=0.7.2
Requires-Dist: drissionpage>=4.0.5.6
Requires-Dist: fake-useragent>=1.5.1
Requires-Dist: furl>=2.1.3
Requires-Dist: httpx[http2,socks]>=0.28.1
Requires-Dist: loguru>=0.7.2
Requires-Dist: parsel>=1.9.1
Requires-Dist: pycryptodomex>=3.20.0
Requires-Dist: pydantic-settings[toml,yaml]>=2.5.2
Requires-Dist: pydantic[dotenv]>=2.9.2
Requires-Dist: requests-go>=1.0.2
Requires-Dist: requests>=2.31.0
Requires-Dist: tenacity>=8.3.0
